ovtable/__init__.py
ovtable/ovtable.py
ovtable-0.0.3.dist-info/LICENSE
ovtable-0.0.3.dist-info/METADATA
ovtable-0.0.3.dist-info/WHEEL
ovtable-0.0.3.dist-info/top_level.txt
ovtable-0.0.3.dist-info/RECORD
