Metadata-Version: 2.1
Name: ovtable
Version: 0.0.3
Summary: based on curses, ovtable is a table displayed in the terminal with Python API
Home-page: https://github.com/PiperLiu/ovtable
Author: Piper Liu
Author-email: piperliu@qq.com
License: UNKNOWN
Platform: UNKNOWN
Classifier: Programming Language :: Python :: 3.6
Classifier: Programming Language :: Python :: 3.7
Classifier: Programming Language :: Python :: 3.8
Classifier: Programming Language :: Python :: 3.9
Classifier: Programming Language :: Python :: 3.10
Classifier: Operating System :: OS Independent
Requires-Python: >=3.6
Requires-Dist: windows-curses ; sys_platform == "win32"
